fastrlapi/__init__.py
fastrlapi/agents.py
fastrlapi/agents_test.py
fastrlapi/core.py
fastrlapi/core_test.py
fastrlapi/env.py
fastrlapi/env_test.py
fastrlapi/backends/core.py
fastrlapi/backends/core_test.py
fastrlapi/backends/debug.py
fastrlapi/backends/default.py
fastrlapi/backends/monitor.py
fastrlapi/backends/monitor_test.py
fastrlapi/backends/tfagents.py
fastrlapi/backends/tfagents_test.py
fastrlapi/backends/tforce.py
fastrlapi/backends/tforce_test.py
fastrlapi/callbacks/duration.py
fastrlapi/callbacks/duration_test.py
fastrlapi/callbacks/log.py
fastrlapi/callbacks/log_test.py
fastrlapi/callbacks/plot.py
fastrlapi/callbacks/plot_test.py
fastrlapi/callbacks/save.py
fastrlapi/callbacks/save_test.py
fastrlapi-0.0.1.dist-info/METADATA
fastrlapi-0.0.1.dist-info/WHEEL
fastrlapi-0.0.1.dist-info/entry_points.txt
fastrlapi-0.0.1.dist-info/top_level.txt
fastrlapi-0.0.1.dist-info/RECORD
