Metadata-Version: 2.1
Name: fastrlapi
Version: 0.0.1
Summary: reinforcement learning high-level API.
Home-page: UNKNOWN
Author: Rohit Gangupantulu
Author-email: rgangupantulu@deloitte.com
License: UNKNOWN
Platform: UNKNOWN
Classifier: License :: OSI Approved :: MIT License
Classifier: Programming Language :: Python :: 3
Classifier: Programming Language :: Python :: 3.7
Requires-Dist: tensorflow (==2.0.1)
Requires-Dist: tensorflow-probability (==0.8.0)
Requires-Dist: tf-agents (==0.3.0)
Requires-Dist: tensorforce (==0.5.3)
Requires-Dist: gym (==0.15.4)
Requires-Dist: imageio (==2.6.1)
Requires-Dist: imageio-ffmpeg (==0.3.0)
Requires-Dist: matplotlib (==3.1.2)
